GeneEnrich/__init__.py
GeneEnrich/base_cli.py
GeneEnrich/consts.py
GeneEnrich/enricher.py
GeneEnrich/parse.py
GeneEnrich/preprocess.py
GeneEnrich/run_go/__init__.py
GeneEnrich/run_go/argparse.py
GeneEnrich/run_go/cli.py
GeneEnrich/run_go/enrich_go.py
GeneEnrich/run_go/go_utilities.py
GeneEnrich/run_kegg/__init__.py
GeneEnrich/run_kegg/argparse.py
GeneEnrich/run_kegg/cli.py
GeneEnrich/run_kegg/enrich_kegg.py
GeneEnrich/run_kegg/kegg_utilities.py
GeneEnrich/update_db/__init__.py
GeneEnrich/update_db/argparse.py
GeneEnrich/update_db/cli.py
pyGeneEnrich-0.0.2.dist-info/LICENSE
pyGeneEnrich-0.0.2.dist-info/METADATA
pyGeneEnrich-0.0.2.dist-info/WHEEL
pyGeneEnrich-0.0.2.dist-info/entry_points.txt
pyGeneEnrich-0.0.2.dist-info/top_level.txt
pyGeneEnrich-0.0.2.dist-info/RECORD
