Metadata-Version: 2.1
Name: pyGeneEnrich
Version: 0.0.2
Summary: A limited python implementation of clusterProfiler from R
Author: WhiteRabBio
License: MIT License
Project-URL: Homepage, https://github.com/WhiteRabBio/GeneEnrich
Classifier: Programming Language :: Python :: 3.9
Classifier: Intended Audience :: Science/Research
Classifier: Topic :: Scientific/Engineering :: Bio-Informatics
Classifier: License :: OSI Approved :: MIT License
Requires-Python: >=3.9
License-File: LICENSE
